linearboost/__init__.py
linearboost/_utils.py
linearboost/linear_boost.py
linearboost/sefr.py
linearboost/licenses/BSD-3-Clause.txt
linearboost-0.1.6.dist-info/METADATA
linearboost-0.1.6.dist-info/WHEEL
linearboost-0.1.6.dist-info/licenses/LICENSE
linearboost-0.1.6.dist-info/RECORD
