Metadata-Version: 2.4
Name: linearboost
Version: 0.1.6
Summary: LinearBoost Classifier is a rapid and accurate classification algorithm that builds upon a very fast, linear classifier.
Project-URL: Homepage, https://github.com/LinearBoost/linearboost-classifier
Project-URL: Documentation, https://linearboost.readthedocs.io
Project-URL: Repository, https://github.com/LinearBoost/linearboost-classifier
Project-URL: Issues, https://github.com/LinearBoost/linearboost-classifier/issues
Author-email: Hamidreza Keshavarz <hamid9@outlook.com>, Reza Rawassizadeh <rezar@bu.edu>
License-File: LICENSE
Keywords: adaboost,boost,boosting,classification,classifier,linear
Classifier: Intended Audience :: Developers
Classifier: Intended Audience :: Science/Research
Classifier: Programming Language :: Python :: 3.8
Classifier: Programming Language :: Python :: 3.9
Classifier: Programming Language :: Python :: 3.10
Classifier: Programming Language :: Python :: 3.11
Classifier: Programming Language :: Python :: 3.12
Classifier: Programming Language :: Python :: 3.13
Classifier: Topic :: Scientific/Engineering
Classifier: Topic :: Scientific/Engineering :: Artificial Intelligence
Classifier: Topic :: Scientific/Engineering :: Information Analysis
Classifier: Topic :: Software Development :: Libraries :: Python Modules
Requires-Python: <3.14,>=3.8
Requires-Dist: scikit-learn>=1.2.2
Requires-Dist: typing-extensions>=4.1.0; python_full_version < '3.11'
